bubble_client.py
bubble_client-0.7.3.dist-info/LICENSE
bubble_client-0.7.3.dist-info/METADATA
bubble_client-0.7.3.dist-info/WHEEL
bubble_client-0.7.3.dist-info/top_level.txt
bubble_client-0.7.3.dist-info/RECORD
