Metadata-Version: 2.1
Name: bubble-client
Version: 0.7.3
Summary: Python client for Bubble.io APIs
Home-page: https://github.com/Refty/bubble-client
Author: Guillaume Gelin
Author-email: guillaume@refty.co
License: UNKNOWN
Platform: UNKNOWN
Classifier: Programming Language :: Python :: 3.7
Classifier: Programming Language :: Python :: 3.8
Classifier: Programming Language :: Python :: 3.9
Classifier: Programming Language :: Python :: 3.10
Classifier: Development Status :: 4 - Beta
Classifier: License :: OSI Approved :: MIT License
Requires-Python: >=3.7, <4
License-File: LICENSE
Requires-Dist: thingy (>=0.8.5)
Requires-Dist: httpx (>=0.21.3)
